DFTPack/__init__.py
dftpack-0.0.0.dist-info/METADATA
dftpack-0.0.0.dist-info/WHEEL
dftpack-0.0.0.dist-info/top_level.txt
dftpack-0.0.0.dist-info/RECORD
