Metadata-Version: 2.1
Name: dftpack
Version: 0.0.0
Summary: Classical Density Functional theory
Home-page: https://github.com/thermotools/DFTPack
